{
    "total": [
        {
            "id": "100003178613865",
            "count": 0
        },
        {
            "id": "100004232470234",
            "count": 5
        },
        {
            "id": "100006593615643",
            "count": 0
        },
        {
            "id": "100008496979488",
            "count": 0
        },
        {
            "id": "100011338718639",
            "count": 7
        },
        {
            "id": "100011863549707",
            "count": 0
        },
        {
            "id": "100015664710694",
            "count": 4
        },
        {
            "id": "100017686326348",
            "count": 44
        },
        {
            "id": "100017820151449",
            "count": 0
        },
        {
            "id": "100022910261257",
            "count": 3
        },
        {
            "id": "100024399162064",
            "count": 0
        },
        {
            "id": "100024536059683",
            "count": 6
        },
        {
            "id": "100027042964108",
            "count": 0
        },
        {
            "id": "100027921631196",
            "count": 0
        },
        {
            "id": "100028208131316",
            "count": 4
        },
        {
            "id": "100029470965460",
            "count": 4
        },
        {
            "id": "100029526843295",
            "count": 0
        },
        {
            "id": "100029617284126",
            "count": 123
        },
        {
            "id": "100033835770271",
            "count": 0
        },
        {
            "id": "100034802018721",
            "count": 0
        },
        {
            "id": "100034826617740",
            "count": 0
        },
        {
            "id": "100037181892631",
            "count": 1
        },
        {
            "id": "100043818528390",
            "count": 95
        },
        {
            "id": "100043855936235",
            "count": 0
        },
        {
            "id": "100044386140552",
            "count": 0
        },
        {
            "id": "100047260833187",
            "count": 0
        },
        {
            "id": "100049010713208",
            "count": 1
        },
        {
            "id": "100049332167154",
            "count": 3
        },
        {
            "id": "100051256207522",
            "count": 0
        },
        {
            "id": "100053754671751",
            "count": 0
        },
        {
            "id": "100054812651893",
            "count": 0
        },
        {
            "id": "100055385845127",
            "count": 0
        },
        {
            "id": "100056435269900",
            "count": 0
        },
        {
            "id": "100061530932491",
            "count": 40
        },
        {
            "id": "100067218906763",
            "count": 0
        },
        {
            "id": "100067985683873",
            "count": 0
        },
        {
            "id": "100068321041466",
            "count": 0
        },
        {
            "id": "100069417160468",
            "count": 16
        },
        {
            "id": "100070788409554",
            "count": 0
        },
        {
            "id": "100072576910956",
            "count": 128
        },
        {
            "id": "100072770006501",
            "count": 3
        },
        {
            "id": "100073021098180",
            "count": 0
        },
        {
            "id": "100073641326701",
            "count": 0
        },
        {
            "id": "100073815881893",
            "count": 0
        },
        {
            "id": "100075805661774",
            "count": 0
        },
        {
            "id": "100075940538217",
            "count": 0
        },
        {
            "id": "100076563096664",
            "count": 0
        },
        {
            "id": "100076966729251",
            "count": 0
        },
        {
            "id": "100078286876345",
            "count": 0
        },
        {
            "id": "100078745832428",
            "count": 0
        },
        {
            "id": "100084266379523",
            "count": 0
        },
        {
            "id": "100084612577307",
            "count": 0
        },
        {
            "id": "100085103471136",
            "count": 318
        },
        {
            "id": "100085503453593",
            "count": 0
        },
        {
            "id": "100085779333728",
            "count": 0
        },
        {
            "id": "100005201702431",
            "count": 21
        }
    ],
    "week": [
        {
            "id": "100003178613865",
            "count": 0
        },
        {
            "id": "100004232470234",
            "count": 5
        },
        {
            "id": "100006593615643",
            "count": 0
        },
        {
            "id": "100008496979488",
            "count": 0
        },
        {
            "id": "100011338718639",
            "count": 7
        },
        {
            "id": "100011863549707",
            "count": 0
        },
        {
            "id": "100015664710694",
            "count": 4
        },
        {
            "id": "100017686326348",
            "count": 44
        },
        {
            "id": "100017820151449",
            "count": 0
        },
        {
            "id": "100022910261257",
            "count": 3
        },
        {
            "id": "100024399162064",
            "count": 0
        },
        {
            "id": "100024536059683",
            "count": 6
        },
        {
            "id": "100027042964108",
            "count": 0
        },
        {
            "id": "100027921631196",
            "count": 0
        },
        {
            "id": "100028208131316",
            "count": 4
        },
        {
            "id": "100029470965460",
            "count": 4
        },
        {
            "id": "100029526843295",
            "count": 0
        },
        {
            "id": "100029617284126",
            "count": 123
        },
        {
            "id": "100033835770271",
            "count": 0
        },
        {
            "id": "100034802018721",
            "count": 0
        },
        {
            "id": "100034826617740",
            "count": 0
        },
        {
            "id": "100037181892631",
            "count": 1
        },
        {
            "id": "100043818528390",
            "count": 95
        },
        {
            "id": "100043855936235",
            "count": 0
        },
        {
            "id": "100044386140552",
            "count": 0
        },
        {
            "id": "100047260833187",
            "count": 0
        },
        {
            "id": "100049010713208",
            "count": 1
        },
        {
            "id": "100049332167154",
            "count": 3
        },
        {
            "id": "100051256207522",
            "count": 0
        },
        {
            "id": "100053754671751",
            "count": 0
        },
        {
            "id": "100054812651893",
            "count": 0
        },
        {
            "id": "100055385845127",
            "count": 0
        },
        {
            "id": "100056435269900",
            "count": 0
        },
        {
            "id": "100061530932491",
            "count": 40
        },
        {
            "id": "100067218906763",
            "count": 0
        },
        {
            "id": "100067985683873",
            "count": 0
        },
        {
            "id": "100068321041466",
            "count": 0
        },
        {
            "id": "100069417160468",
            "count": 16
        },
        {
            "id": "100070788409554",
            "count": 0
        },
        {
            "id": "100072576910956",
            "count": 128
        },
        {
            "id": "100072770006501",
            "count": 3
        },
        {
            "id": "100073021098180",
            "count": 0
        },
        {
            "id": "100073641326701",
            "count": 0
        },
        {
            "id": "100073815881893",
            "count": 0
        },
        {
            "id": "100075805661774",
            "count": 0
        },
        {
            "id": "100075940538217",
            "count": 0
        },
        {
            "id": "100076563096664",
            "count": 0
        },
        {
            "id": "100076966729251",
            "count": 0
        },
        {
            "id": "100078286876345",
            "count": 0
        },
        {
            "id": "100078745832428",
            "count": 0
        },
        {
            "id": "100084266379523",
            "count": 0
        },
        {
            "id": "100084612577307",
            "count": 0
        },
        {
            "id": "100085103471136",
            "count": 318
        },
        {
            "id": "100085503453593",
            "count": 0
        },
        {
            "id": "100085779333728",
            "count": 0
        },
        {
            "id": "100005201702431",
            "count": 21
        }
    ],
    "day": [
        {
            "id": "100003178613865",
            "count": 0
        },
        {
            "id": "100004232470234",
            "count": 5
        },
        {
            "id": "100006593615643",
            "count": 0
        },
        {
            "id": "100008496979488",
            "count": 0
        },
        {
            "id": "100011338718639",
            "count": 7
        },
        {
            "id": "100011863549707",
            "count": 0
        },
        {
            "id": "100015664710694",
            "count": 4
        },
        {
            "id": "100017686326348",
            "count": 44
        },
        {
            "id": "100017820151449",
            "count": 0
        },
        {
            "id": "100022910261257",
            "count": 3
        },
        {
            "id": "100024399162064",
            "count": 0
        },
        {
            "id": "100024536059683",
            "count": 6
        },
        {
            "id": "100027042964108",
            "count": 0
        },
        {
            "id": "100027921631196",
            "count": 0
        },
        {
            "id": "100028208131316",
            "count": 4
        },
        {
            "id": "100029470965460",
            "count": 4
        },
        {
            "id": "100029526843295",
            "count": 0
        },
        {
            "id": "100029617284126",
            "count": 123
        },
        {
            "id": "100033835770271",
            "count": 0
        },
        {
            "id": "100034802018721",
            "count": 0
        },
        {
            "id": "100034826617740",
            "count": 0
        },
        {
            "id": "100037181892631",
            "count": 1
        },
        {
            "id": "100043818528390",
            "count": 95
        },
        {
            "id": "100043855936235",
            "count": 0
        },
        {
            "id": "100044386140552",
            "count": 0
        },
        {
            "id": "100047260833187",
            "count": 0
        },
        {
            "id": "100049010713208",
            "count": 1
        },
        {
            "id": "100049332167154",
            "count": 3
        },
        {
            "id": "100051256207522",
            "count": 0
        },
        {
            "id": "100053754671751",
            "count": 0
        },
        {
            "id": "100054812651893",
            "count": 0
        },
        {
            "id": "100055385845127",
            "count": 0
        },
        {
            "id": "100056435269900",
            "count": 0
        },
        {
            "id": "100061530932491",
            "count": 40
        },
        {
            "id": "100067218906763",
            "count": 0
        },
        {
            "id": "100067985683873",
            "count": 0
        },
        {
            "id": "100068321041466",
            "count": 0
        },
        {
            "id": "100069417160468",
            "count": 16
        },
        {
            "id": "100070788409554",
            "count": 0
        },
        {
            "id": "100072576910956",
            "count": 128
        },
        {
            "id": "100072770006501",
            "count": 3
        },
        {
            "id": "100073021098180",
            "count": 0
        },
        {
            "id": "100073641326701",
            "count": 0
        },
        {
            "id": "100073815881893",
            "count": 0
        },
        {
            "id": "100075805661774",
            "count": 0
        },
        {
            "id": "100075940538217",
            "count": 0
        },
        {
            "id": "100076563096664",
            "count": 0
        },
        {
            "id": "100076966729251",
            "count": 0
        },
        {
            "id": "100078286876345",
            "count": 0
        },
        {
            "id": "100078745832428",
            "count": 0
        },
        {
            "id": "100084266379523",
            "count": 0
        },
        {
            "id": "100084612577307",
            "count": 0
        },
        {
            "id": "100085103471136",
            "count": 318
        },
        {
            "id": "100085503453593",
            "count": 0
        },
        {
            "id": "100085779333728",
            "count": 0
        },
        {
            "id": "100005201702431",
            "count": 21
        }
    ],
    "time": 6
}